bitscrunch_sdk/__init__.py
tests/__init__.py
bitscrunch_sdk_unleashnft_v2-0.1.0.dist-info/METADATA
bitscrunch_sdk_unleashnft_v2-0.1.0.dist-info/WHEEL
bitscrunch_sdk_unleashnft_v2-0.1.0.dist-info/top_level.txt
bitscrunch_sdk_unleashnft_v2-0.1.0.dist-info/RECORD
